sphinx_autotoc/__init__.py
sphinx_autotoc-0.0.1a1.dist-info/LICENSE
sphinx_autotoc-0.0.1a1.dist-info/METADATA
sphinx_autotoc-0.0.1a1.dist-info/WHEEL
sphinx_autotoc-0.0.1a1.dist-info/top_level.txt
sphinx_autotoc-0.0.1a1.dist-info/RECORD
