Metadata-Version: 2.1
Name: sphinx-autotoc
Version: 0.0.1a1
Summary: Расширение для Sphinx для создания оглавлений (TOC)
Author: IRS Ural
Project-URL: Homepage, https://github.com/irsural/sphinx-autotoc
Classifier: Programming Language :: Python :: 3
Classifier: License :: OSI Approved :: MIT License
Classifier: Operating System :: OS Independent
Requires-Python: >=3.8
License-File: LICENSE
